easycaching/__init__.py
easycaching/db.py
easycaching/db_proxy.py
easycaching/proxy.py
easycaching/quorum.py
easycaching-0.108.dist-info/LICENSE
easycaching-0.108.dist-info/METADATA
easycaching-0.108.dist-info/WHEEL
easycaching-0.108.dist-info/top_level.txt
easycaching-0.108.dist-info/RECORD
