Metadata-Version: 2.1
Name: easycaching
Version: 0.108
Summary: Shared, persistent, and smart caching via a single shared interface for storing and retreiving data from memory among many processes(forks) of an application
Home-page: https://github.com/codemation/easycaching
Author: Joshua Jamison
Author-email: joshjamison1@gmail.com
License: UNKNOWN
Platform: UNKNOWN
Classifier: Programming Language :: Python :: 3
Classifier: License :: OSI Approved :: MIT License
Classifier: Operating System :: OS Independent
Requires-Python: >=3.7, <4
Requires-Dist: easyrpc (>=0.241)
Requires-Dist: aiopyql (>=0.359)
Requires-Dist: gunicorn
Requires-Dist: python-multipart
